peach_partner/__init__.py
peach_partner/result_codes.py
peach_partner/validator/__init__.py
peach_partner/validator/schemas.py
peach_partner/validator/validator.py
peach_partner-0.0.5.dist-info/WHEEL
peach_partner-0.0.5.dist-info/METADATA
peach_partner-0.0.5.dist-info/RECORD
